muffin_admin/__init__.py
muffin_admin/admin.html
muffin_admin/handler.py
muffin_admin/main.js
muffin_admin/main.js.LICENSE.txt
muffin_admin/plugin.py
muffin_admin/py.typed
muffin_admin/types.py
muffin_admin/utils.py
muffin_admin/peewee/__init__.py
muffin_admin/peewee/log.py
muffin_admin/peewee/schemas.py
muffin_admin/sqlalchemy/__init__.py
muffin_admin-11.3.1.dist-info/METADATA
muffin_admin-11.3.1.dist-info/WHEEL
muffin_admin-11.3.1.dist-info/RECORD
