Metadata-Version: 2.4
Name: muffin-admin
Version: 11.3.1
Summary: Admin interface for Muffin Framework
Project-URL: Homepage, https://github.com/klen/muffin-admin
Project-URL: Repository, https://github.com/klen/muffin-admin
Author-email: Kirill Klenov <horneds@gmail.com>
License-Expression: MIT
Keywords: admin,api,asgi,asyncio,muffin,trio
Classifier: Development Status :: 5 - Production/Stable
Classifier: Framework :: AsyncIO
Classifier: Framework :: Trio
Classifier: Intended Audience :: Developers
Classifier: License :: OSI Approved :: MIT License
Classifier: Programming Language :: Python
Classifier: Programming Language :: Python :: 3
Classifier: Programming Language :: Python :: 3.10
Classifier: Programming Language :: Python :: 3.11
Classifier: Programming Language :: Python :: 3.12
Classifier: Programming Language :: Python :: 3.13
Classifier: Topic :: Internet :: WWW/HTTP
Requires-Python: >3.10
Requires-Dist: muffin
Requires-Dist: muffin-rest
Requires-Dist: typing-extensions; python_version <= '3.10'
Provides-Extra: peewee
Requires-Dist: marshmallow-peewee; extra == 'peewee'
Requires-Dist: muffin-peewee-aio; extra == 'peewee'
Provides-Extra: sqlalchemy
Requires-Dist: marshmallow-sqlalchemy; extra == 'sqlalchemy'
Requires-Dist: muffin-databases; extra == 'sqlalchemy'
Requires-Dist: sqlalchemy; extra == 'sqlalchemy'
Provides-Extra: yaml
Requires-Dist: pyyaml; extra == 'yaml'
